sphinx_lua_ls/__init__.py
sphinx_lua_ls/_version.py
sphinx_lua_ls/apidoc.py
sphinx_lua_ls/autodoc.py
sphinx_lua_ls/autoindex.py
sphinx_lua_ls/config.py
sphinx_lua_ls/domain.py
sphinx_lua_ls/inherited.py
sphinx_lua_ls/intersphinx.py
sphinx_lua_ls/lua_ls.py
sphinx_lua_ls/nodes.py
sphinx_lua_ls/objtree.py
sphinx_lua_ls/py.typed
sphinx_lua_ls/pygments.py
sphinx_lua_ls/utils.py
sphinx_lua_ls/static/lua.css
sphinx_lua_ls-3.10.0.dist-info/licenses/LICENSE
sphinx_lua_ls-3.10.0.dist-info/METADATA
sphinx_lua_ls-3.10.0.dist-info/WHEEL
sphinx_lua_ls-3.10.0.dist-info/top_level.txt
sphinx_lua_ls-3.10.0.dist-info/RECORD
