Metadata-Version: 2.4
Name: sphinx-lua-ls
Version: 3.10.0
Summary: Automatic documentation generation via EmmyLua/LuaLs
Author-email: Tamika Nomara <taminomara@gmail.com>
License-Expression: MIT
Project-URL: Documentation, https://sphinx-lua-ls.readthedocs.io/en/stable/
Project-URL: Issues, https://github.com/sphinx-contrib/lua-ls/issues
Project-URL: Source, https://github.com/sphinx-contrib/lua-ls/
Project-URL: Changelog, https://github.com/sphinx-contrib/lua-ls/blob/main/CHANGELOG.md
Classifier: Development Status :: 5 - Production/Stable
Classifier: Programming Language :: Python :: 3 :: Only
Classifier: Programming Language :: Python :: 3
Classifier: Programming Language :: Python :: 3.12
Classifier: Programming Language :: Python :: 3.13
Classifier: Intended Audience :: Developers
Classifier: Framework :: Sphinx
Classifier: Framework :: Sphinx :: Domain
Classifier: Framework :: Sphinx :: Extension
Classifier: Topic :: Software Development :: Documentation
Classifier: Topic :: Documentation
Classifier: Topic :: Documentation :: Sphinx
Classifier: Typing :: Typed
Requires-Python: >=3.12
License-File: LICENSE
Requires-Dist: sphinx<10.0,>=8.0
Requires-Dist: PyGithub<3.0,>=1.59
Requires-Dist: requests~=2.31
Dynamic: license-file
